pynamer/README.md
pynamer/__init__.py
pynamer/__main__.py
pynamer/builder.py
pynamer/cli.py
pynamer/config.py
pynamer/pynamer.py
pynamer/setup.txt
pynamer/setup_base.txt
pynamer/utils.py
pynamer/validators.py
pynamer/project_name/__init__.py
pynamer-2.1.8.dist-info/LICENSE
pynamer-2.1.8.dist-info/METADATA
pynamer-2.1.8.dist-info/WHEEL
pynamer-2.1.8.dist-info/entry_points.txt
pynamer-2.1.8.dist-info/top_level.txt
pynamer-2.1.8.dist-info/RECORD
