Metadata-Version: 2.1
Name: pynamer
Version: 2.1.8
Summary: Utility to find an available package name in the PyPI repository and register it
Home-page: https://github.com/Stephen-RA-King/pynamer
Download-URL: https://github.com/Stephen-RA-King/pynamer/archive/refs/heads/main.zip
Author: Stephen R A King
Author-email: sking.github@gmail.com
Maintainer: Stephen R A King
Maintainer-email: sking.github@gmail.com
License: MIT
Project-URL: Bug Tracker, https://github.com/Stephen-RA-King/pynamer/issues
Project-URL: CI, https://github.com/Stephen-RA-King/pynamer/actions
Project-URL: Documentation, https://pynamer.readthedocs.io/en/latest/
Project-URL: Release Notes, https://github.com/Stephen-RA-King/pynamer/releases
Project-URL: Source Code, https://github.com/Stephen-RA-King/pynamer/
Keywords: available-on-pypi,pip-search,packaging,naming,name-generation,names,pypi,packaging,naming-conventions
Platform: Any
Classifier: Development Status :: 5 - Production/Stable
Classifier: Environment :: Console
Classifier: Intended Audience :: Developers
Classifier: License :: OSI Approved :: MIT License
Classifier: Operating System :: OS Independent
Classifier: Natural Language :: English
Classifier: Programming Language :: Python :: 3
Classifier: Programming Language :: Python :: 3 :: Only
Classifier: Programming Language :: Python :: 3.9
Classifier: Programming Language :: Python :: 3.10
Classifier: Programming Language :: Python :: 3.11
Requires-Python: >=3.9
License-File: LICENSE
Requires-Dist: beautifulsoup4 (>=4.12.2)
Requires-Dist: build (>=0.10.0)
Requires-Dist: colorama (>=0.4.6)
Requires-Dist: jinja2 (>=3.1.2)
Requires-Dist: packaging (>=23.1)
Requires-Dist: python-dateutil (>=2.8.2)
Requires-Dist: pyyaml (>=6.0)
Requires-Dist: requests (>=2.30.0)
Requires-Dist: rich (>=13.3.5)
Requires-Dist: tqdm (>=4.65.0)
Requires-Dist: twine (>=3.8.0)
Requires-Dist: wheel (>=0.40.0)
